<list>
  <person>
    <uuid>c4147f3a-029c-4c8e-8710-3b29a02019d3</uuid>
    <firstName>Josh</firstName>
    <lastName>Terminator</lastName>
    <phoneNumber>111-111-1111</phoneNumber>
    <emailAddresses>
      <string>joshtheterminator@yahoo.com</string>
    </emailAddresses>
  </person>
  <person>
    <uuid>17a2a995-6555-46e2-8630-bfd3d8765d78</uuid>
    <firstName>Eminem</firstName>
    <lastName>Boseman</lastName>
    <phoneNumber>222-222-2222</phoneNumber>
    <emailAddresses>
      <string>eminemnottherapper@gmail.com</string>
    </emailAddresses>
  </person>
  <person>
    <uuid>365ecbd2-ed99-4cd6-8d63-d9da8c9caa89</uuid>
    <firstName>Michael</firstName>
    <lastName>Starburst</lastName>
    <phoneNumber>333-333-3333</phoneNumber>
    <emailAddresses>
      <string>michael33@aol.com</string>
      <string>michael33clone@aol.com</string>
    </emailAddresses>
  </person>
  <person>
    <uuid>ef1e65c3-38c4-49ba-b25d-d6696e1918b4</uuid>
    <firstName>Ermias</firstName>
    <lastName>Wolde</lastName>
    <phoneNumber>444-444-4444</phoneNumber>
    <emailAddresses>
      <string>ewolde2@huskers.unl.edu</string>
    </emailAddresses>
  </person>
  <person>
    <uuid>ee444afd-39d1-4ed6-b611-7f5a8db842f8</uuid>
    <firstName>Oscar</firstName>
    <lastName>Hanson</lastName>
    <phoneNumber>555-555-5555</phoneNumber>
    <emailAddresses>
      <string>ohanson5@huskers.unl.edu</string>
    </emailAddresses>
  </person>
</list>